{
    "os": "Linux-6.2.0-39-generic-x86_64-with-glibc2.37",
    "python": "3.11.4",
    "heartbeatAt": "2024-08-09T08:29:39.628844",
    "startedAt": "2024-08-09T08:29:35.733745",
    "docker": null,
    "cuda": null,
    "args": [],
    "state": "running",
    "program": "/home/milan/Neural-Style-Transfer/NST_model2.py",
    "codePathLocal": "NST_model2.py",
    "codePath": "NST_model2.py",
    "git": {
        "remote": "git@github.com:milanlakhani/Neural-Style-Transfer.git",
        "commit": "57ea9c191f0aef20d95f32188b09e00219e6dcf0"
    },
    "email": "milan.l@hotmail.co.uk",
    "root": "/home/milan/Neural-Style-Transfer",
    "host": "milan-20N3S3XR00",
    "username": "milan",
    "executable": "/home/milan/Neural-Style-Transfer/nstmil/bin/python",
    "cpu_count": 4,
    "cpu_count_logical": 8,
    "cpu_freq": {
        "current": 792.27925,
        "min": 400.0,
        "max": 4800.0
    },
    "cpu_freq_per_core": [
        {
            "current": 800.019,
            "min": 400.0,
            "max": 4800.0
        },
        {
            "current": 800.042,
            "min": 400.0,
            "max": 4800.0
        },
        {
            "current": 799.987,
            "min": 400.0,
            "max": 4800.0
        },
        {
            "current": 799.998,
            "min": 400.0,
            "max": 4800.0
        },
        {
            "current": 800.073,
            "min": 400.0,
            "max": 4800.0
        },
        {
            "current": 799.992,
            "min": 400.0,
            "max": 4800.0
        },
        {
            "current": 800.002,
            "min": 400.0,
            "max": 4800.0
        },
        {
            "current": 800.007,
            "min": 400.0,
            "max": 4800.0
        }
    ],
    "disk": {
        "/": {
            "total": 912.7941513061523,
            "used": 175.0055274963379
        }
    },
    "memory": {
        "total": 38.79707336425781
    }
}
